ai_shell/__about__.py
ai_shell/__init__.py
ai_shell/__main__.py
ai_shell/ai_logs/__init__.py
ai_shell/ai_logs/json_log_handler.py
ai_shell/ai_logs/log_to_bash.py
ai_shell/ai_logs/log_to_markdown.py
ai_shell/ai_logs/logging_utils.py
ai_shell/ai_logs/pretty_errors_log.py
ai_shell/answer_tool.py
ai_shell/backup_restore.py
ai_shell/bot_glue/__init__.py
ai_shell/bot_glue/bot.py
ai_shell/bot_glue/tool_utils.py
ai_shell/cat_tool.py
ai_shell/code_generate/__init__.py
ai_shell/code_generate/generate_cli.py
ai_shell/code_generate/generate_schema.py
ai_shell/code_generate/generate_toolkit.py
ai_shell/code_generate/method_to_jsonschema.py
ai_shell/cut_tool.py
ai_shell/demo_bots/__init__.py
ai_shell/demo_bots/check_tools.py
ai_shell/demo_bots/demo_setup.py
ai_shell/demo_bots/docs_writer_bot.py
ai_shell/demo_bots/pylint_bot.py
ai_shell/demo_bots/test_writer_bot.py
ai_shell/demo_bots/test_writer_bot_instructions.md
ai_shell/demo_bots/test_writer_bot_mission.md
ai_shell/demo_bots/todo_bot.py
ai_shell/demo_bots/todo_bot_instructions.md
ai_shell/demo_bots/todo_bot_mission.md
ai_shell/demo_bots/tool_tester_bot.py
ai_shell/demo_bots/tool_tester_bot_instructions.md
ai_shell/demo_bots/tool_tester_bot_mission.md
ai_shell/diff_tool.py
ai_shell/ed_tool.py
ai_shell/edlin_tool.py
ai_shell/externals/__init__.py
ai_shell/externals/black_call.py
ai_shell/externals/mypy_call.py
ai_shell/externals/pygount_call.py
ai_shell/externals/pylint_call.py
ai_shell/externals/pytest_call.py
ai_shell/externals/ruff_call.py
ai_shell/externals/subprocess_utils.py
ai_shell/find_tool.py
ai_shell/fish_tank.zip
ai_shell/git_tool.py
ai_shell/grep_tool.py
ai_shell/head_tail_tool.py
ai_shell/import_plugins.py
ai_shell/insert_tool.py
ai_shell/ls_tool.py
ai_shell/openai_schemas.py
ai_shell/openai_support.py
ai_shell/openai_toolkit.py
ai_shell/openai_tools.py
ai_shell/patch_tool.py
ai_shell/plugins/__init__.py
ai_shell/plugins/hello_tool.py
ai_shell/py.typed
ai_shell/pycat_tool.py
ai_shell/pytest_tool.py
ai_shell-1.0.4.dist-info/LICENSE
ai_shell-1.0.4.dist-info/METADATA
ai_shell-1.0.4.dist-info/WHEEL
ai_shell-1.0.4.dist-info/entry_points.txt
ai_shell-1.0.4.dist-info/RECORD
