Metadata-Version: 2.1
Name: ai_shell
Version: 1.0.4
Summary: Filesystem Shell interface that an OpenAI Assitant can use as a tool.
Home-page: https://github.com/matthewdeanmartin/ai_shell
License: MIT
Keywords: openai,chatgpt
Author: Matthew Martin
Author-email: matthewdeanmartin@gmail.com
Requires-Python: >=3.11,<3.12
Classifier: Development Status :: 3 - Alpha
Classifier: Intended Audience :: Developers
Classifier: License :: OSI Approved :: MIT License
Classifier: Operating System :: OS Independent
Classifier: Programming Language :: Python
Classifier: Programming Language :: Python :: 3
Classifier: Programming Language :: Python :: 3.11
Requires-Dist: astor (>=0.8.1)
Requires-Dist: bug-trail-core (>=2.0.0)
Requires-Dist: cli-tool-audit (>=3.0.0)
Requires-Dist: dedlin (>=1.19.0)
Requires-Dist: docstring-parser (>=0.15)
Requires-Dist: ed (>=0.1.0)
Requires-Dist: gitpython (>=3.1.31)
Requires-Dist: html2text (>=2020.1.16,<2021.0.0)
Requires-Dist: inflect (>=7.0.0,<8.0.0)
Requires-Dist: jinja2 (>=3.1.2)
Requires-Dist: jsonschema (>=4.20.0)
Requires-Dist: markdown-it-py (>=3.0.0,<4.0.0)
Requires-Dist: markpickle (>=1.6.1,<2.0.0)
Requires-Dist: mdformat (>=0.7.16)
Requires-Dist: mdit-plain (>=1.0.1,<2.0.0)
Requires-Dist: openai (>=1.3.3)
Requires-Dist: openai_multi_tool_use_parallel_patch
Requires-Dist: orjson (>=3.9.10)
Requires-Dist: pygount (>=1.6.1)
Requires-Dist: pylint (>=3.0.2)
Requires-Dist: pytest (>=7.4.3)
Requires-Dist: pytest-cov (>=4.1.0)
Requires-Dist: python-minifier (>=2.9.0)
Requires-Dist: pyyaml (>=6.0.1)
Requires-Dist: ruff (>=0.1.9)
Requires-Dist: stdlib-list (>=0.10.0,<0.11.0)
Requires-Dist: tiktoken (>=0.4.0)
Requires-Dist: toml (>=0.10.2)
Requires-Dist: unidiff (>=0.7.5)
Requires-Dist: untruncate-json (>=1.0.0,<2.0.0)
Project-URL: Bug Tracker, https://github.com/matthewdeanmartin/ai_shell/issues
Project-URL: Change Log, https://github.com/matthewdeanmartin/ai_shell/blob/main/CHANGELOG.md
Project-URL: Documentation, https://github.com/matthewdeanmartin/ai_shell
Project-URL: Repository, https://github.com/matthewdeanmartin/ai_shell
